experiments/__init__.py
experiments/experiment_imdb.py
experiments/experiment_mnist.py
experiments/experiment_parity.py
experiments/experiment_xor.py
pytsetlin/__init__.py
pytsetlin/tsetlin_machine.py
pytsetlin/core/__init__.py
pytsetlin/core/config.py
pytsetlin/core/executor.py
pytsetlin/core/feedback.py
pytsetlin/core/tuner.py
pytsetlin/data/__init__.py
pytsetlin/data/imdb.py
pytsetlin/data/mnist.py
pytsetlin/data/parity.py
pytsetlin/data/xor.py
pytsetlin-1.1.1.dist-info/LICENSE
pytsetlin-1.1.1.dist-info/METADATA
pytsetlin-1.1.1.dist-info/WHEEL
pytsetlin-1.1.1.dist-info/top_level.txt
pytsetlin-1.1.1.dist-info/RECORD
