Metadata-Version: 2.2
Name: pytsetlin
Version: 1.1.1
Summary: A low-code Pythonic implementation of a Coalesced Tsetlin Machine
Home-page: https://github.com/Sebastianostby/pytsetlin
Author: Sebastian Østby
Author-email: Sebastianostby@gmail.com
Classifier: Programming Language :: Python :: 3
Classifier: License :: OSI Approved :: MIT License
Classifier: Operating System :: OS Independent
Requires-Python: >=3.8
License-File: LICENSE
Requires-Dist: numba==0.60.0
Requires-Dist: scipy==1.15.0
Requires-Dist: tqdm==4.67.1
Requires-Dist: scikit-learn==1.6.0
Requires-Dist: pandas==2.2.3
Requires-Dist: pytest==8.3.4
Requires-Dist: datasets==3.2.0
Requires-Dist: optuna==4.2.1
Dynamic: author
Dynamic: author-email
Dynamic: classifier
Dynamic: description
Dynamic: description-content-type
Dynamic: home-page
Dynamic: requires-dist
Dynamic: requires-python
Dynamic: summary
